interpret_eval/__init__.py
interpret_eval/interpret_eval_main.py
interpret_eval/tasks/__init__.py
interpret_eval/tasks/absa/__init__.py
interpret_eval/tasks/absa/conf.aspects
interpret_eval/tasks/absa/template.json
interpret_eval/tasks/absa/tensoreval.py
interpret_eval/tasks/chunk/__init__.py
interpret_eval/tasks/chunk/conf.aspects
interpret_eval/tasks/chunk/template.json
interpret_eval/tasks/chunk/tensoreval.py
interpret_eval/tasks/cws/__init__.py
interpret_eval/tasks/cws/conf.aspects
interpret_eval/tasks/cws/template.json
interpret_eval/tasks/cws/tensoreval.py
interpret_eval/tasks/ner/__init__.py
interpret_eval/tasks/ner/conf.aspects
interpret_eval/tasks/ner/template.json
interpret_eval/tasks/ner/tensoreval.py
interpret_eval/tasks/nli/__init__.py
interpret_eval/tasks/nli/conf.aspects
interpret_eval/tasks/nli/template.json
interpret_eval/tasks/nli/tensoreval.py
interpret_eval/tasks/pos/__init__.py
interpret_eval/tasks/pos/conf.aspects
interpret_eval/tasks/pos/template.json
interpret_eval/tasks/pos/tensoreval.py
interpret_eval/tasks/re/__init__.py
interpret_eval/tasks/re/a.json
interpret_eval/tasks/re/conf.aspects
interpret_eval/tasks/re/errorAnalysis.py
interpret_eval/tasks/re/instantiate.json
interpret_eval/tasks/re/template.json
interpret_eval/tasks/re/tensoreval-backup.py
interpret_eval/tasks/re/tensoreval.py
interpret_eval/tasks/src/__init__.py
interpret_eval/tasks/src/errorAnalysis.py
interpret_eval/tasks/src/ner_overall_f1.py
interpret_eval/tasks/src/utils.py
interpret_eval/tasks/tc/__init__.py
interpret_eval/tasks/tc/conf.aspects
interpret_eval/tasks/tc/template.json
interpret_eval/tasks/tc/tensoreval.py
interpret_eval-0.1.7.dist-info/METADATA
interpret_eval-0.1.7.dist-info/WHEEL
interpret_eval-0.1.7.dist-info/entry_points.txt
interpret_eval-0.1.7.dist-info/top_level.txt
interpret_eval-0.1.7.dist-info/RECORD
