Metadata-Version: 2.1
Name: interpret-eval
Version: 0.1.7
Summary: Interpretable Evaluation for Natural Language Processing
Home-page: https://github.com/neulab/ExplainaBoard
Author: Pengfei Liu
License: MIT License
Platform: UNKNOWN
Classifier: Intended Audience :: Developers
Classifier: Topic :: Text Processing
Classifier: Topic :: Scientific/Engineering :: Artificial Intelligence
Classifier: License :: OSI Approved :: MIT License
Classifier: Programming Language :: Python :: 3
Requires-Dist: nltk (>=3.2)
Requires-Dist: numpy
Requires-Dist: scipy
Requires-Dist: matplotlib
Requires-Dist: scikit-learn
Requires-Dist: seqeval (==0.0.12)
